databrickslabs_jupyterlab_status/__init__.py
databrickslabs_jupyterlab_status/_version.py
databrickslabs_jupyterlab_status/labextension/package.json
databrickslabs_jupyterlab_status/labextension/static/114.1e363cbbfe4e9bcce1c2.js
databrickslabs_jupyterlab_status/labextension/static/534.6b8d3b219e0aefc66cc8.js
databrickslabs_jupyterlab_status/labextension/static/726.6617024e24c60b8912f5.js
databrickslabs_jupyterlab_status/labextension/static/726.9f0a49553c659378064f.js
databrickslabs_jupyterlab_status/labextension/static/remoteEntry.11b087b46d82b17ef7e2.js
databrickslabs_jupyterlab_status/labextension/static/remoteEntry.9932ad06ae61d0fd6577.js
databrickslabs_jupyterlab_status/labextension/static/style.js
databrickslabs_jupyterlab_status-2.2.1.data/data/share/jupyter/labextensions/databricks_status/install.json
databrickslabs_jupyterlab_status-2.2.1.data/data/share/jupyter/labextensions/databricks_status/package.json
databrickslabs_jupyterlab_status-2.2.1.data/data/share/jupyter/labextensions/databricks_status/static/114.1e363cbbfe4e9bcce1c2.js
databrickslabs_jupyterlab_status-2.2.1.data/data/share/jupyter/labextensions/databricks_status/static/534.6b8d3b219e0aefc66cc8.js
databrickslabs_jupyterlab_status-2.2.1.data/data/share/jupyter/labextensions/databricks_status/static/726.6617024e24c60b8912f5.js
databrickslabs_jupyterlab_status-2.2.1.data/data/share/jupyter/labextensions/databricks_status/static/remoteEntry.9932ad06ae61d0fd6577.js
databrickslabs_jupyterlab_status-2.2.1.data/data/share/jupyter/labextensions/databricks_status/static/style.js
databrickslabs_jupyterlab_status-2.2.1.dist-info/LICENSE
databrickslabs_jupyterlab_status-2.2.1.dist-info/METADATA
databrickslabs_jupyterlab_status-2.2.1.dist-info/WHEEL
databrickslabs_jupyterlab_status-2.2.1.dist-info/top_level.txt
databrickslabs_jupyterlab_status-2.2.1.dist-info/RECORD
