Metadata-Version: 2.1
Name: databrickslabs-jupyterlab-status
Version: 2.2.1
Summary: A JupyterLab extension to show starting status of Databricks clusters.
Home-page: https://github.com/databrickslabs/Jupyterlab-Integration
Author: Bernhard Walter
Author-email: bernhard.walter@databricks.com
License: BSD-3-Clause
Keywords: Jupyter,JupyterLab,JupyterLab3
Platform: Linux
Platform: Mac OS X
Platform: Windows
Classifier: License :: OSI Approved :: BSD License
Classifier: Programming Language :: Python
Classifier: Programming Language :: Python :: 3
Classifier: Programming Language :: Python :: 3.6
Classifier: Programming Language :: Python :: 3.7
Classifier: Programming Language :: Python :: 3.8
Classifier: Programming Language :: Python :: 3.9
Classifier: Framework :: Jupyter
Requires-Python: >=3.6
Requires-Dist: jupyterlab (~=3.0)
Requires-Dist: jupyter-packaging (<2,~=0.9)
